crow_api/core/__init__.py
crow_api/core/py.typed
crow_api/core/_jsii/__init__.py
crow_api/core/_jsii/crow-api@2.4.0.jsii.tgz
crow_api.core-2.4.0.data/scripts/crow-api
crow_api.core-2.4.0.dist-info/LICENSE
crow_api.core-2.4.0.dist-info/METADATA
crow_api.core-2.4.0.dist-info/WHEEL
crow_api.core-2.4.0.dist-info/top_level.txt
crow_api.core-2.4.0.dist-info/RECORD
